README.md
setup.py
sippy/OLSims_methods.py
sippy/Parsim_methods.py
sippy/__init__.py
sippy/armax.py
sippy/armaxMIMO.py
sippy/arx.py
sippy/arxMIMO.py
sippy/functionset.py
sippy/functionsetSIM.py
sippy/functionset_OPT.py
sippy/io_opt.py
sippy/io_optMIMO.py
sippy/io_rls.py
sippy/io_rlsMIMO.py
sippy/tests/__init__.py
sippy/tests/test_armax.py
sippy_rcognita.egg-info/PKG-INFO
sippy_rcognita.egg-info/SOURCES.txt
sippy_rcognita.egg-info/dependency_links.txt
sippy_rcognita.egg-info/requires.txt
sippy_rcognita.egg-info/top_level.txt